envseal/__init__.py
envseal/__main__.py
envseal/cli.py
envseal/core.py
envseal/utils/__init__.py
envseal/utils/helpers.py
envseal-1.1.0.dist-info/METADATA
envseal-1.1.0.dist-info/WHEEL
envseal-1.1.0.dist-info/entry_points.txt
envseal-1.1.0.dist-info/licenses/LICENSE
envseal-1.1.0.dist-info/RECORD
